README.rst
setup.py
django_sofort.egg-info/PKG-INFO
django_sofort.egg-info/SOURCES.txt
django_sofort.egg-info/dependency_links.txt
django_sofort.egg-info/requires.txt
django_sofort.egg-info/top_level.txt
sofort/__init__.py
sofort/admin.py
sofort/models.py
sofort/signals.py
sofort/tests.py
sofort/urls.py
sofort/views.py