Metadata-Version: 1.1
Name: django-sofort
Version: 0.0.1
Summary: Django implementation of the Sofort.com API
Home-page: https://github.com/codingjoe/django-sofort
Author: codingjoe
Author-email: info@johanneshoppe.com
License: MIT License
Platform: UNKNOWN
Classifier: Development Status :: 2 - Pre-Alpha
Classifier: Environment :: Web Environment
Classifier: Framework :: Django
Classifier: Topic :: Office/Business :: Financial :: Accounting
Classifier: Intended Audience :: Developers
Classifier: Intended Audience :: Financial and Insurance Industry
Classifier: License :: OSI Approved :: MIT License
Classifier: Operating System :: OS Independent
Classifier: Programming Language :: Python
Classifier: Topic :: Software Development
Requires: django (>=1.3.1)
Requires: dict2xml (>=1.1)
Requires: pymoneyed (>=0.5)
Requires: beautifulsoup4 (>=4.0)
Requires: pythondateutil (>=2.2)
